tive/__init__.py
tive-0.0.0a0.dist-info/WHEEL
tive-0.0.0a0.dist-info/METADATA
tive-0.0.0a0.dist-info/RECORD
