Metadata-Version: 2.1
Name: tive
Version: 0.0.0a0
Summary: Tive API
Author: Tive, Inc.
Requires-Python: >=3.7
Classifier: Programming Language :: Python
Classifier: Programming Language :: Python :: 3
